sendinblue/__about__.py
sendinblue/__init__.py
sendinblue/apps.py
sendinblue/client.py
sendinblue/forms.py
sendinblue/jinja.py
sendinblue/models.py
sendinblue/py2client.py
sendinblue/urls.py
sendinblue/utils.py
sendinblue/views.py
sendinblue/wagtail_hooks.py
sendinblue/widgets.py
sendinblue/locale/fr/LC_MESSAGES/django.mo
sendinblue/locale/fr/LC_MESSAGES/django.po
sendinblue/migrations/0001_initial.py
sendinblue/migrations/0002_form_introduction.py
sendinblue/migrations/0003_send_mails.py
sendinblue/migrations/__init__.py
sendinblue/static/sendinblue/css/admin.css
sendinblue/static/sendinblue/css/style.css
sendinblue/static/sendinblue/js/sendinblue.js
sendinblue/templates/sendinblue/admin-iframe.html
sendinblue/templates/sendinblue/admin-welcome.html
sendinblue/templates/sendinblue/admin.html
sendinblue/templates/sendinblue/template_tag.html
sendinblue/templates/sendinblue/thankyou.html
sendinblue/templates/sendinblue/blocks/form-field.html
sendinblue/templates/sendinblue/blocks/form.html
sendinblue/templates/sendinblue/blocks/iframe-form.html
sendinblue/templates/sendinblue/blocks/textarea.html
sendinblue/templates/sendinblue/widgets/account.html
sendinblue/templates/sendinblue/widgets/automation.html
sendinblue/templates/sendinblue/widgets/campaign.html
sendinblue/templates/sendinblue/widgets/contacts.html
sendinblue/templatetags/__init__.py
sendinblue/templatetags/jinja.py
sendinblue/templatetags/sendinblue.py
wagtail_sendinblue-0.1.0.dev0.dist-info/DESCRIPTION.rst
wagtail_sendinblue-0.1.0.dev0.dist-info/METADATA
wagtail_sendinblue-0.1.0.dev0.dist-info/RECORD
wagtail_sendinblue-0.1.0.dev0.dist-info/WHEEL
wagtail_sendinblue-0.1.0.dev0.dist-info/metadata.json
wagtail_sendinblue-0.1.0.dev0.dist-info/top_level.txt
