Metadata-Version: 2.0
Name: wagtail-sendinblue
Version: 0.1.0.dev0
Summary: SendInBlue integration for Wagtail
Home-page: https://github.com/apihackers/wagtail-sendinblue
Author: API Hackers
Author-email: wagtail-sendinblue@apihackers.com
License: MIT
Keywords: wagtail sendinblue
Platform: UNKNOWN
Classifier: Development Status :: 3 - Alpha
Classifier: Programming Language :: Python
Classifier: Environment :: Web Environment
Classifier: Operating System :: OS Independent
Classifier: Intended Audience :: Developers
Classifier: Topic :: System :: Software Distribution
Classifier: Programming Language :: Python
Classifier: Programming Language :: Python :: 2
Classifier: Programming Language :: Python :: 2.6
Classifier: Programming Language :: Python :: 2.7
Classifier: Programming Language :: Python :: 3
Classifier: Programming Language :: Python :: 3.3
Classifier: Programming Language :: Python :: 3.4
Classifier: Programming Language :: Python :: 3.5
Classifier: Programming Language :: Python :: Implementation :: PyPy
Classifier: Topic :: Software Development :: Libraries :: Python Modules
Classifier: License :: OSI Approved :: MIT License
Requires-Dist: requests
Provides-Extra: doc
Provides-Extra: test
